{
	"api_set_name": "pbcore",
	"impl_prefix": "sysent",
	"type_aliases": {
		"ps_ufd_t": "i32",
		"ps_proc_id_t": "u32"
	},
	"entries": {
		"0": {
			"name": "exit",
			"params": [
				"i32"
			],
			"return": "void"
		},
		"1": {
			"name": "open",
			"params": [
				"*char",
				"usize",
				"u32",
				"u32",
				"*ps_ufd_t"
			],
			"return": "result"
		},
		"2": {
			"name": "close",
			"params": [
				"ps_ufd_t",
				"u32"
			],
			"return": "result"
		},
		"3": {
			"name": "read",
			"params": [
				"ps_ufd_t",
				"*void",
				"u32"
			],
			"return": "result"
		},
		"4": {
			"name": "write",
			"params": [
				"ps_ufd_t",
				"*void",
				"u32"
			],
			"return": "result"
		},
		"5": {
			"name": "exec_child",
			"params": [
				"ps_ufd_t",
				"ps_ufd_t",
				"&char",
				"usize",
				"*ps_proc_id_t"
			],
			"return": "result"
		},
		"6": {
			"name": "fork",
			"params": [],
			"return": "result"
		}
	}
}
